filtarr/__init__.py
filtarr/checker.py
filtarr/cli.py
filtarr/config.py
filtarr/criteria.py
filtarr/logging.py
filtarr/output.py
filtarr/py.typed
filtarr/state.py
filtarr/tagger.py
filtarr/webhook.py
filtarr/clients/__init__.py
filtarr/clients/base.py
filtarr/clients/factory.py
filtarr/clients/radarr.py
filtarr/clients/sonarr.py
filtarr/models/__init__.py
filtarr/models/common.py
filtarr/models/radarr.py
filtarr/models/sonarr.py
filtarr/models/webhook.py
filtarr/scheduler/__init__.py
filtarr/scheduler/executor.py
filtarr/scheduler/exporter.py
filtarr/scheduler/manager.py
filtarr/scheduler/models.py
filtarr/scheduler/triggers.py
filtarr-3.0.0.dist-info/METADATA
filtarr-3.0.0.dist-info/WHEEL
filtarr-3.0.0.dist-info/entry_points.txt
filtarr-3.0.0.dist-info/licenses/LICENSE
filtarr-3.0.0.dist-info/RECORD
