Metadata-Version: 2.4
Name: filtarr
Version: 3.0.0
Summary: A Python library to check release availability via Radarr/Sonarr search results
Project-URL: Homepage, https://github.com/dabigc/filtarr
Project-URL: Repository, https://github.com/dabigc/filtarr
Project-URL: Issues, https://github.com/dabigc/filtarr/issues
Author: dabigc
License-Expression: MIT
License-File: LICENSE
Keywords: 4k,automation,filter,jellyfin,media,plex,radarr,sonarr
Classifier: Development Status :: 4 - Beta
Classifier: Intended Audience :: Developers
Classifier: Intended Audience :: System Administrators
Classifier: License :: OSI Approved :: MIT License
Classifier: Operating System :: OS Independent
Classifier: Programming Language :: Python :: 3
Classifier: Programming Language :: Python :: 3.11
Classifier: Programming Language :: Python :: 3.12
Classifier: Programming Language :: Python :: 3.13
Classifier: Topic :: Home Automation
Classifier: Topic :: Multimedia :: Video
Classifier: Typing :: Typed
Requires-Python: >=3.11
Requires-Dist: cachetools>=5.3.0
Requires-Dist: httpx>=0.27.0
Requires-Dist: pydantic>=2.0.0
Requires-Dist: tenacity>=8.2.0
Provides-Extra: cli
Requires-Dist: rich>=13.0.0; extra == 'cli'
Requires-Dist: typer>=0.12.0; extra == 'cli'
Provides-Extra: dev
Requires-Dist: apscheduler>=4.0.0a5; extra == 'dev'
Requires-Dist: croniter>=2.0.0; extra == 'dev'
Requires-Dist: fastapi>=0.115.0; extra == 'dev'
Requires-Dist: httpx[http2]>=0.27.0; extra == 'dev'
Requires-Dist: mypy>=1.13.0; extra == 'dev'
Requires-Dist: pre-commit>=4.0.0; extra == 'dev'
Requires-Dist: pytest-asyncio>=0.24.0; extra == 'dev'
Requires-Dist: pytest-cov>=6.0.0; extra == 'dev'
Requires-Dist: pytest>=8.0.0; extra == 'dev'
Requires-Dist: respx>=0.22.0; extra == 'dev'
Requires-Dist: rich>=13.0.0; extra == 'dev'
Requires-Dist: ruff>=0.8.0; extra == 'dev'
Requires-Dist: typer>=0.12.0; extra == 'dev'
Requires-Dist: types-cachetools>=5.5.0; extra == 'dev'
Requires-Dist: types-croniter>=2.0.0; extra == 'dev'
Requires-Dist: uvicorn[standard]>=0.32.0; extra == 'dev'
Provides-Extra: scheduler
Requires-Dist: apscheduler>=4.0.0a5; extra == 'scheduler'
Requires-Dist: croniter>=2.0.0; extra == 'scheduler'
Provides-Extra: webhook
Requires-Dist: fastapi>=0.115.0; extra == 'webhook'
Requires-Dist: uvicorn[standard]>=0.32.0; extra == 'webhook'
